[
  {
    "line": "S71",
    "date": "2026-02-26",
    "stand": "2026-02-26T17:36:00.000Z",
    "trainNumber": "85597",
    "fromStop": "KA Tullastr.",
    "fromTime": "22:17",
    "toStop": "Rastatt Bf",
    "toTime": "22:57",
    "sourceUrl": "https://www.kvv.de/fahrplan/verkehrsmeldungen.html?tx_ixkvvticker_list%5Baction%5D=detail&tx_ixkvvticker_list%5Bcontroller%5D=Ticker&tx_ixkvvticker_list%5BdetailID%5D=Nettro_CMS_264274",
    "capturedAt": "2026-02-26T20:32:26.276Z"
  },
  {
    "line": "S71",
    "date": "2026-03-14",
    "stand": "2026-03-14T10:45:00.000Z",
    "trainNumber": "85593",
    "fromStop": "Karlsruhe Hbf.",
    "fromTime": "22:47",
    "toStop": "Baden-Baden Bahnhof",
    "toTime": "23:17",
    "sourceUrl": "https://www.kvv.de/fahrplan/verkehrsmeldungen.html?tx_ixkvvticker_list%5Baction%5D=detail&tx_ixkvvticker_list%5Bcontroller%5D=Ticker&tx_ixkvvticker_list%5BdetailID%5D=Nettro_CMS_265274",
    "capturedAt": "2026-03-14T12:41:02.017Z"
  },
  {
    "line": "S71",
    "date": "2026-04-25",
    "stand": "2026-04-25T16:00:00.000Z",
    "trainNumber": "85593",
    "fromStop": "Karlsruhe Hbf",
    "fromTime": "22:47",
    "toStop": "Baden-Baden",
    "toTime": "23:17",
    "sourceUrl": "https://www.kvv.de/fahrplan/verkehrsmeldungen.html?tx_ixkvvticker_list%5Baction%5D=detail&tx_ixkvvticker_list%5Bcontroller%5D=Ticker&tx_ixkvvticker_list%5BdetailID%5D=Nettro_CMS_267755",
    "capturedAt": "2026-04-25T16:36:03.901Z"
  }
]
